[
	{
		"id": "11349829",
		"issue": "17",
		"publishDate": "Dec 2000",
		"publisher": "Image Comics ",
		"readDate": "May 07, 2017",
		"series": "Sam & Twitch",
		"title": "Bounty Hunter Wars, Bounty Hunter Wars: Part Three",
		"cover": "https://clzcomics.r.sizr.io/core/covers/lg/85/85_105568_0_BountyHunterWarsPartThree.jpg"
	},
	{
		"id": "11349828",
		"issue": "18",
		"publishDate": "Jan 2001",
		"publisher": "Image Comics ",
		"readDate": "May 07, 2017",
		"series": "Sam & Twitch",
		"title": "Bounty Hunter Wars, Bounty Hunter Wars: Part Four",
		"cover": "https://clzcomics.r.sizr.io/core/covers/lg/45/45_105569_0_SamTwitch18BountyHunterWarsPar.jpg"
	},
	{
		"id": "11349839",
		"issue": "7",
		"publishDate": "Feb 2000",
		"publisher": "Image Comics ",
		"readDate": "May 07, 2017",
		"series": "Sam & Twitch",
		"title": "Udaku, Udaku: Part Seven",
		"cover": "https://clzcomics.r.sizr.io/core/covers/lg/62/62_105558_0_SamTwitch7UdakuPartSeven.jpg"
	},
	{
		"id": "11349838",
		"issue": "8",
		"publishDate": "Mar 2000",
		"publisher": "Image Comics ",
		"readDate": "May 07, 2017",
		"series": "Sam & Twitch",
		"title": "Udaku, Udaku: Part Eight",
		"cover": "https://clzcomics.r.sizr.io/core/covers/lg/27/27_105559_0_SamTwitch8UdakuPartEight.jpg"
	},
	{
		"id": "11349837",
		"issue": "9",
		"publishDate": "Apr 2000",
		"publisher": "Image Comics ",
		"readDate": "May 07, 2017",
		"series": "Sam & Twitch",
		"title": "One Really Bad Day",
		"cover": "https://clzcomics.r.sizr.io/core/covers/lg/c6/c6_105560_0_SamTwitch9OneReallyBadDay.jpg"
	},
	{
		"id": "11349836",
		"issue": "10",
		"publishDate": "May 2000",
		"publisher": "Image Comics ",
		"readDate": "May 07, 2017",
		"series": "Sam & Twitch",
		"title": "Witchcraft, Witchcraft: Part One",
		"cover": "https://clzcomics.r.sizr.io/core/covers/lg/e6/e6_105561_0_SamTwitch10WitchcraftPartOne.jpg"
	},
	{
		"id": "11349835",
		"issue": "11",
		"publishDate": "Jun 2000",
		"publisher": "Image Comics ",
		"readDate": "May 07, 2017",
		"series": "Sam & Twitch",
		"title": "Witchcraft, Witchcraft: Part Two",
		"cover": "https://clzcomics.r.sizr.io/core/covers/lg/8d/8d_105562_0_SamTwitch11WitchcraftPartTwo.jpg"
	},
	{
		"id": "11349834",
		"issue": "12",
		"publishDate": "Jul 2000",
		"publisher": "Image Comics ",
		"readDate": "May 07, 2017",
		"series": "Sam & Twitch",
		"title": "Witchcraft, Witchcraft: Part Three",
		"cover": "https://clzcomics.r.sizr.io/core/covers/lg/ac/ac_105563_0_SamTwitch12WitchcraftPartThree.jpg"
	},
	{
		"id": "11349845",
		"issue": "1",
		"publishDate": "Aug 1999",
		"publisher": "Image Comics ",
		"readDate": "May 07, 2017",
		"series": "Sam & Twitch",
		"title": "Udaku, Udaku: Part One",
		"cover": "https://clzcomics.r.sizr.io/core/covers/lg/e4/e4_105552_0_SamTwitch1UdakuPartOne.jpg"
	},
	{
		"id": "11349844",
		"issue": "2",
		"publishDate": "Sep 1999",
		"publisher": "Image Comics ",
		"readDate": "May 07, 2017",
		"series": "Sam & Twitch",
		"title": "Udaku, Udaku: Part Two",
		"cover": "https://clzcomics.r.sizr.io/core/covers/lg/ad/ad_105553_0_SamTwitch2UdakuPartTwo.jpg"
	},
	{
		"id": "11349843",
		"issue": "3",
		"publishDate": "Oct 1999",
		"publisher": "Image Comics ",
		"readDate": "May 07, 2017",
		"series": "Sam & Twitch",
		"title": "Udaku, Udaku: Part Three",
		"cover": "https://clzcomics.r.sizr.io/core/covers/lg/9c/9c_105554_0_SamTwitch3UdakuPartThree.jpg"
	},
	{
		"id": "11349842",
		"issue": "4",
		"publishDate": "Nov 1999",
		"publisher": "Image Comics ",
		"readDate": "May 07, 2017",
		"series": "Sam & Twitch",
		"title": "Udaku, Udaku: Part Four",
		"cover": "https://clzcomics.r.sizr.io/core/covers/lg/ed/ed_105555_0_SamTwitch4UdakuPartFour.jpg"
	},
	{
		"id": "11349841",
		"issue": "5",
		"publishDate": "Dec 1999",
		"publisher": "Image Comics ",
		"readDate": "May 07, 2017",
		"series": "Sam & Twitch",
		"title": "Udaku, Udaku: Part Five",
		"cover": "https://clzcomics.r.sizr.io/core/covers/lg/59/59_105556_0_SamTwitch5UdakuPartFive.jpg"
	},
	{
		"id": "11349840",
		"issue": "6",
		"publishDate": "Jan 2000",
		"publisher": "Image Comics ",
		"readDate": "May 07, 2017",
		"series": "Sam & Twitch",
		"title": "Udaku, Udaku: Part Six",
		"cover": "https://clzcomics.r.sizr.io/core/covers/lg/a4/a4_105557_0_SamTwitch6UdakuPartSix.jpg"
	},
	{
		"id": "11350206",
		"issue": "",
		"publishDate": "Nov 1994",
		"publisher": "Marvel Comics ",
		"readDate": "May 07, 2017",
		"series": "Beavis & Butt-Head",
		"title": "Holidazed and Confused",
		"cover": "https://clzcomics.r.sizr.io/core/covers/lg/7d/7d_205664_0_BeavisButtHeadHolidazedandConf.jpg"
	},
	{
		"id": "11350205",
		"issue": "1",
		"publishDate": "Mar 1994",
		"publisher": "Marvel Comics ",
		"readDate": "May 07, 2017",
		"series": "Beavis & Butt-Head",
		"title": "Dental Hygiene Dilemma",
		"cover": "https://clzcomics.r.sizr.io/core/covers/lg/59/59_120840_0_BeavisandButthead1.jpg"
	},
	{
		"id": "11350204",
		"issue": "2",
		"publishDate": "Apr 1994",
		"publisher": "Marvel Comics ",
		"readDate": "May 07, 2017",
		"series": "Beavis & Butt-Head",
		"title": "Dead From The Neck Up!",
		"cover": "https://clzcomics.r.sizr.io/core/covers/lg/df/df_121348_0_BeavisandButthead2DeadFromTheN.jpg"
	},
	{
		"id": "11350203",
		"issue": "3",
		"publishDate": "May 1994",
		"publisher": "Marvel Comics ",
		"readDate": "May 07, 2017",
		"series": "Beavis & Butt-Head",
		"title": "Break Out At Burger World!",
		"cover": "https://clzcomics.r.sizr.io/core/covers/lg/a8/a8_121760_0_BeavisandButthead3BurgerWorld.jpg"
	},
	{
		"id": "11350202",
		"issue": "4",
		"publishDate": "Jun 1994",
		"publisher": "Marvel Comics ",
		"readDate": "May 07, 2017",
		"series": "Beavis & Butt-Head",
		"title": "Tattoo Parlor",
		"cover": "https://clzcomics.r.sizr.io/core/covers/lg/0e/0e_122082_0_BeavisandButthead4TatooParlor.jpg"
	},
	{
		"id": "11350211",
		"issue": "6",
		"publishDate": "Apr 2007",
		"publisher": "Marvel Comics ",
		"readDate": "May 07, 2017",
		"series": "X-Men: First Class, Vol. 1",
		"title": "The S-Men",
		"cover": "https://clzcomics.r.sizr.io/core/covers/lg/9b/9b_143550_0_XMenFirstClass6TheSMen.jpg"
	},
	{
		"id": "11350210",
		"issue": "7",
		"publishDate": "May 2007",
		"publisher": "Marvel Comics ",
		"readDate": "May 07, 2017",
		"series": "X-Men: First Class, Vol. 1",
		"title": "Who Wants to Date a Millionaire?",
		"cover": "https://clzcomics.r.sizr.io/core/covers/lg/9a/9a_145812_0_XMenFirstClassVol17WhoWantstoD.jpg"
	},
	{
		"id": "11350209",
		"issue": "8",
		"publishDate": "Jun 2007",
		"publisher": "Marvel Comics ",
		"readDate": "May 07, 2017",
		"series": "X-Men: First Class, Vol. 1",
		"title": "The Treasure Hunters",
		"cover": "https://clzcomics.r.sizr.io/core/covers/lg/f9/f9_148504_0_XMenFirstClassVol18TheTreasure.jpg"
	},
	{
		"id": "11350208",
		"issue": "3A",
		"publishDate": "Dec 30, 2015",
		"publisher": "Archie Comic Publications ",
		"readDate": "May 07, 2017",
		"series": "Jughead, Vol. 3",
		"title": "",
		"cover": "https://clzcomics.r.sizr.io/core/covers/lg/96/96_424958_0_.jpg"
	},
	{
		"id": "11350207",
		"issue": "4A",
		"publishDate": "Feb 10, 2016",
		"publisher": "Archie Comic Publications ",
		"readDate": "May 07, 2017",
		"series": "Jughead, Vol. 3",
		"title": "",
		"cover": "https://clzcomics.r.sizr.io/core/covers/lg/bb/bb_427714_0_.jpg"
	},
	{
		"id": "11350217",
		"issue": "7A",
		"publishDate": "Jan 2007",
		"publisher": "Marvel Comics ",
		"readDate": "May 07, 2017",
		"series": "Civil War, Vol. 1",
		"title": "Civil War - Civil War, Part Seven",
		"cover": "https://clzcomics.r.sizr.io/core/covers/lg/d5/d5_143515_0_CivilWar7ACivilWarPartSeven.jpg"
	},
	{
		"id": "11350216",
		"issue": "1",
		"publishDate": "Nov 2006",
		"publisher": "Marvel Comics ",
		"readDate": "May 07, 2017",
		"series": "X-Men: First Class, Vol. 1",
		"title": "X-Men 101",
		"cover": "https://clzcomics.r.sizr.io/core/covers/lg/0d/0d_135099_0_XMenFirstClass1XMen101.jpg"
	},
	{
		"id": "11350215",
		"issue": "2",
		"publishDate": "Dec 2006",
		"publisher": "Marvel Comics ",
		"readDate": "May 07, 2017",
		"series": "X-Men: First Class, Vol. 1",
		"title": "The Bird, The Beast And The Lizard",
		"cover": "https://clzcomics.r.sizr.io/core/covers/lg/c3/c3_136267_0_XMenFirstClass2TheBirdTheBeast.jpg"
	},
	{
		"id": "11350214",
		"issue": "3",
		"publishDate": "Jan 2007",
		"publisher": "Marvel Comics ",
		"readDate": "May 07, 2017",
		"series": "X-Men: First Class, Vol. 1",
		"title": "A Life of the Mind",
		"cover": "https://clzcomics.r.sizr.io/core/covers/lg/17/17_138346_0_XMenFirstClass3ALifeoftheMind.jpg"
	},
	{
		"id": "11350213",
		"issue": "4",
		"publishDate": "Feb 2007",
		"publisher": "Marvel Comics ",
		"readDate": "May 07, 2017",
		"series": "X-Men: First Class, Vol. 1",
		"title": "Seeing Red",
		"cover": "https://clzcomics.r.sizr.io/core/covers/lg/33/33_140255_0_XMenFirstClass4SeeingRed.jpg"
	},
	{
		"id": "11350212",
		"issue": "5",
		"publishDate": "Mar 2007",
		"publisher": "Marvel Comics ",
		"readDate": "May 07, 2017",
		"series": "X-Men: First Class, Vol. 1",
		"title": "The Littlest Frost Giant",
		"cover": "https://clzcomics.r.sizr.io/core/covers/lg/4d/4d_142412_0_XMenFirstClass5TheLittlestFros.jpg"
	}
]
